homismart_client/__init__.py
homismart_client/client.py
homismart_client/commands.py
homismart_client/enums.py
homismart_client/exceptions.py
homismart_client/session.py
homismart_client/utils.py
homismart_client/devices/__init__.py
homismart_client/devices/base_device.py
homismart_client/devices/curtain.py
homismart_client/devices/hub.py
homismart_client/devices/lock.py
homismart_client/devices/switchable.py
homismart_client-0.1.5.dist-info/licenses/LICENSE
homismart_client-0.1.5.dist-info/METADATA
homismart_client-0.1.5.dist-info/WHEEL
homismart_client-0.1.5.dist-info/top_level.txt
homismart_client-0.1.5.dist-info/RECORD
